rtl/DataMemoria.v
module DataMemoria (
    input  wire        clk,
    input  wire        MemRead,
    input  wire        MemWrite,
    input  wire [31:0] addr,
    input  wire [31:0] writeData,
    output reg  [31:0] readData
);

    // 256 palavras de 32 bits
    reg [31:0] memory [0:255];


    always @(*) begin
        if (MemRead)
            readData = memory[addr[31:2]];
        else
            readData = 32'b0;
    end

    always @(posedge clk) begin
        if (MemWrite)
            memory[addr[31:2]] <= writeData;
    end

endmodule

rtl/UnidadeBranch.v
module UnidadeBranch (
    input  wire        branch,
    input  wire [2:0]  funct3,
    input  wire [31:0] rs1,
    input  wire [31:0] rs2,
    output reg         branchTaken
);

    always @(*) begin
        branchTaken = 1'b0;

        if (branch) begin
            case (funct3)
                3'b000: branchTaken = (rs1 == rs2);                       // BEQ
                3'b001: branchTaken = (rs1 != rs2);                       // BNE
                3'b100: branchTaken = ($signed(rs1) < $signed(rs2));      // BLT
                3'b101: branchTaken = ($signed(rs1) >= $signed(rs2));     // BGE
                3'b110: branchTaken = (rs1 < rs2);                        // BLTU
                3'b111: branchTaken = (rs1 >= rs2);                       // BGEU
                default: branchTaken = 1'b0;
            endcase
        end
    end

endmodule

rtl/Alu.v
module ALU(
    input  [31:0] A,
    input  [31:0] B,
    input  [3:0]  ALUControl,
    output reg [31:0] Resultado,
    output Zero
);

    always @(*) begin
        case(ALUControl)
            4'b0000: Resultado = A + B;               // ADD
            4'b0001: Resultado = A - B;               // SUB
            4'b0010: Resultado = A & B;               // AND
            4'b0011: Resultado = A | B;               // OR
            4'b0100: Resultado = A ^ B;               // XOR
            4'b0101: Resultado = (A < B) ? 1 : 0;     // SLT
            4'b0110: Resultado = A << B[4:0];         // SLL
            4'b0111: Resultado = A >> B[4:0];         // SRL
            4'b1000: Resultado = $signed(A) >>> B[4:0]; // SRA
            default: Resultado = 0;
        endcase
    end

    assign Zero = (Resultado == 0);

endmodule

rtl/AluControl.v
module ALUControl(
    input [1:0] ALUOp,
    input [2:0] funct3,
    input [6:0] funct7,
    output reg [3:0] aluControl
);

always @(*) begin
    case(ALUOp)

        2'b00: aluControl = 4'b0000; // ADD (lw, sw, addi)

        2'b01: aluControl = 4'b0001; // SUB (branch)

        2'b10: begin
            case(funct3)

                3'b000: begin
                    if (funct7 == 7'b0100000)
                        aluControl = 4'b0001; // SUB
                    else
                        aluControl = 4'b0000; // ADD
                end

                3'b111: aluControl = 4'b0010; // AND
                3'b110: aluControl = 4'b0011; // OR
                3'b100: aluControl = 4'b0100; // XOR

                default: aluControl = 4'b0000;

            endcase
        end

        default: aluControl = 4'b0000;

    endcase
end

endmodule

rtl/GeradorImetiato.v
module GeradorImediato(
    input  [31:0] instrucoes,
    output reg [31:0] imediato
);

    wire [6:0] opcode = instrucoes[6:0];

    always @(*) begin
        case(opcode)

            // I-type
            7'b0010011, 
            7'b0000011,
            7'b1100111: begin
                imediato = {{20{instrucoes[31]}}, instrucoes[31:20]};
            end

            // S-type
            7'b0100011: begin
                imediato = {{20{instrucoes[31]}},
                       instrucoes[31:25],
                       instrucoes[11:7]};
            end

            // B-type
            7'b1100011: begin
                imediato = {{19{instrucoes[31]}},
                       instrucoes[31],
                       instrucoes[7],
                       instrucoes[30:25],
                       instrucoes[11:8],
                       1'b0};
            end

            // U-type
            7'b0110111,
            7'b0010111: begin
                imediato = {instrucoes[31:12], 12'b0};
            end

            // J-type
            7'b1101111: begin
                imediato = {{11{instrucoes[31]}},
                       instrucoes[31],
                       instrucoes[19:12],
                       instrucoes[20],
                       instrucoes[30:21],
                       1'b0};
            end

            default: imediato = 32'b0;

        endcase
    end

endmodule

rtl/Registradores.v
module Registradores (
    input wire clk,
    input wire regWrite,
    input wire [4:0] rs1,
    input wire [4:0] rs2,
    input wire [4:0] rd,
    input wire [31:0] writeData,
    output wire [31:0] readData1,
    output wire [31:0] readData2
);

    
    reg [31:0] registradores [0:31];

    integer i;

    // Inicializando
    initial begin
        for (i = 0; i < 32; i = i + 1)
            registradores[i] = 32'd0;
    end

    // Leitura 
    assign readData1 = (rs1 == 5'd0) ? 32'd0 : registradores[rs1];
    assign readData2 = (rs2 == 5'd0) ? 32'd0 : registradores[rs2];

    // Escrita 
    always @(posedge clk) begin
        if (regWrite && rd != 5'd0)
            registradores[rd] <= writeData;
    end

endmodule

rtl/UnidadeControle.v
module UnidadeControle (
    input  [6:0] Opcode,
    output reg RegWrite,
    output reg ALUSrc,
    output reg MemRead,
    output reg MemWrite,
    output reg MemToReg,
    output reg Branch,
    output reg Jump,
    output reg [1:0] ALUOp
);

    always @(*) begin

        RegWrite = 0;
        ALUSrc   = 0;
        MemRead  = 0;
        MemWrite = 0;
        MemToReg = 0;
        Branch   = 0;
        Jump     = 0;
        ALUOp    = 2'b00;

        case(Opcode)

            7'b0110011: begin // R-type
                RegWrite = 1;
                ALUSrc   = 0;
                ALUOp    = 2'b10;
            end

            7'b0010011: begin // I-type
                RegWrite = 1;
                ALUSrc   = 1;
                ALUOp    = 2'b11;
            end

            7'b0000011: begin // LW
                RegWrite = 1;
                ALUSrc   = 1;
                MemRead  = 1;
                MemToReg = 1;
                ALUOp    = 2'b00;
            end

            7'b0100011: begin // SW
                MemWrite = 1;
                ALUSrc   = 1;
                ALUOp    = 2'b00;
            end

            7'b1100011: begin // Branch
                Branch = 1;
                ALUOp  = 2'b01;
            end

            7'b1101111: begin // JAL
                RegWrite = 1;
                Jump     = 1;
            end

            7'b1100111: begin // JALR
                RegWrite = 1;
                ALUSrc   = 1;
                Jump     = 1;
            end

            7'b0110111: begin // LUI
                RegWrite = 1;
                ALUSrc   = 1;
            end

            7'b0010111: begin // AUIPC
                RegWrite = 1;
                ALUSrc   = 1;
            end

        endcase
    end

endmodule

rtl/MemoriaIntrucao.v
module MemoriaIntrucao (
    input  wire [31:0] addr,          
    output wire [31:0] instrucao    
);

    // 256 instruções de 32 bits 
    reg [31:0] memoria [0:255];

    // Inicialização 
    integer i;
    initial begin
        for (i = 0; i < 256; i = i + 1)
            memoria[i] = 32'b0;

        $readmemh("Fibonacci.mem", memoria);
    end
    assign instrucao = memoria[addr[31:2]];

endmodule

rtl/Pc.v
module Pc (
    input  wire        clk,
    input  wire        reset,
    input  wire        halt,
    input  wire        branch,
    input  wire        zero,
    input  wire        jump,       // JAL
    input  wire        jalr,       // JALR
    input  wire [31:0] immediate,
    input  wire [31:0] rs1,
    output reg  [31:0] pc
);

    reg [31:0] nextPc;

    always @(*) begin
        if (halt)
            nextPc = pc;
        else if (jalr)
            nextPc = rs1 + immediate;
        else if (jump)
            nextPc = pc + immediate;
        else if (branch && zero)
            nextPc = pc + immediate;
        else
            nextPc = pc + 32'd4;
    end

    always @(posedge clk or posedge reset) begin
        if (reset)
            pc <= 32'd0;
        else
            pc <= nextPc;
    end

endmodule

rtl/Riscv-32I.v
module RiscV_CPU (
    input wire clk,
    input wire reset
);

    // ==============================
    // WIRES INTERNOS
    // ==============================

    wire [31:0] pc;
    wire [31:0] instruction;
    wire [31:0] immediate;

    wire [31:0] rs1_data;
    wire [31:0] rs2_data;
    wire [31:0] alu_result;
    wire [31:0] memory_read;

    wire RegWrite;
    wire ALUSrc;
    wire MemRead;
    wire MemWrite;
    wire MemToReg;
    wire Branch;
    wire Jump;
    wire jalr;

    wire [1:0] ALUOp;

    wire branchTaken;
    wire zero;

    // ==============================
    // PC
    // ==============================

    Pc pcouter (
        .clk(clk),
        .reset(reset),
        .halt(1'b0),
        .branch(branchTaken),
        .zero(zero),
        .jump(Jump),
        .jalr(jalr),
        .rs1(rs1_data),
        .immediate(immediate),
        .pc(pc)
    );

    // ==============================
    // Instruction Memory
    // ==============================

    MemoriaIntrucao imem (
        .addr(pc),
        .instrucao(instruction)
    );

    // ==============================
    // Control Unit
    // ==============================

    UnidadeControle control (
        .Opcode(instruction[6:0]),
        .RegWrite(RegWrite),
        .ALUSrc(ALUSrc),
        .MemRead(MemRead),
        .MemWrite(MemWrite),
        .MemToReg(MemToReg),
        .Branch(Branch),
        .Jump(Jump),
        .ALUOp(ALUOp)
    );

    // ==============================
    // REGISTER FILE
    // ==============================

    wire [31:0] writeBackData;

    assign writeBackData = (MemToReg) ? memory_read : alu_result;

    Registradores regfile (
        .clk(clk),
        .regWrite(RegWrite),
        .rs1(instruction[19:15]),
        .rs2(instruction[24:20]),
        .rd(instruction[11:7]),
        .writeData(writeBackData),
        .readData1(rs1_data),
        .readData2(rs2_data)
    );

    // ==============================
    // IMMEDIATE GENERATOR
    // ==============================

    GeradorImediato immGen (
        .instrucoes(instruction),
        .imediato(immediate)
    );

    // ==============================
    // AluControl
    // ==============================

    ALUControl alu_control_unit (
        .ALUOp(ALUOp),
        .funct3(instruction[14:12]),
        .funct7(instruction[31:25]),
        .aluControl(aluControl)
    );

    // ==============================
    // ALU
    // ==============================

    wire [31:0] srcB;
    wire [3:0] aluControl;

    assign srcB = (ALUSrc) ? immediate : rs2_data;

    ALU alu (
        .A(rs1_data),
        .B(srcB),
        .ALUControl(aluControl),
        .Resultado(alu_result),
        .Zero(zero)
    );

    // ==============================
    // BRANCH UNIT
    // ==============================

    UnidadeBranch branch_unit (
        .branch(Branch),
        .funct3(instruction[14:12]),
        .rs1(rs1_data),
        .rs2(rs2_data),
        .branchTaken(branchTaken)
    );

    // ==============================
    // DATA MEMORY
    // ==============================

    DataMemoria dmem (
        .clk(clk),
        .MemRead(MemRead),
        .MemWrite(MemWrite),
        .addr(alu_result),
        .writeData(rs2_data),
        .readData(memory_read)
    );

endmodule

sim/tb_cpu.v
module tb_cpu;

    reg clk;
    reg reset;

    RiscV_CPU cpu (
        .clk(clk),
        .reset(reset)
    );

    initial begin
        clk = 0;
        forever #5 clk = ~clk;
    end

    initial begin
        reset = 1;
        #10;
        reset = 0;

        #500;
        $finish;
    end

    initial begin
        $dumpfile("cpu.vcd");
        $dumpvars(0, tb_cpu);
    end
    initial begin
        #500;
        $display("x1 = %d", cpu.regfile.registradores[1]);
        $display("x2 = %d", cpu.regfile.registradores[2]);
        $display("x3 = %d", cpu.regfile.registradores[3]);
        $display("x4 = %d", cpu.regfile.registradores[4]);
        $display("x5 = %d", cpu.regfile.registradores[5]);
        $display("O valor de fibonacci eh: %d", cpu.regfile.registradores[4]);
    end
endmodule

cpu.vcd
$date
	Mon Mar  9 17:45:08 2026
$end
$version
	Icarus Verilog
$end
$timescale
	1s
$end
$scope module tb_cpu $end
$var reg 1 ! clk $end
$var reg 1 " reset $end
$scope module cpu $end
$var wire 1 ! clk $end
$var wire 1 # jalr $end
$var wire 1 " reset $end
$var wire 1 $ zero $end
$var wire 32 % writeBackData [31:0] $end
$var wire 32 & srcB [31:0] $end
$var wire 32 ' rs2_data [31:0] $end
$var wire 32 ( rs1_data [31:0] $end
$var wire 32 ) pc [31:0] $end
$var wire 32 * memory_read [31:0] $end
$var wire 32 + instruction [31:0] $end
$var wire 32 , immediate [31:0] $end
$var wire 1 - branchTaken $end
$var wire 32 . alu_result [31:0] $end
$var wire 4 / aluControl [3:0] $end
$var wire 1 0 RegWrite $end
$var wire 1 1 MemWrite $end
$var wire 1 2 MemToReg $end
$var wire 1 3 MemRead $end
$var wire 1 4 Jump $end
$var wire 1 5 Branch $end
$var wire 1 6 ALUSrc $end
$var wire 2 7 ALUOp [1:0] $end
$scope module alu $end
$var wire 32 8 B [31:0] $end
$var wire 1 $ Zero $end
$var wire 4 9 ALUControl [3:0] $end
$var wire 32 : A [31:0] $end
$var reg 32 ; Resultado [31:0] $end
$upscope $end
$scope module alu_control_unit $end
$var wire 3 < funct3 [2:0] $end
$var wire 7 = funct7 [6:0] $end
$var wire 2 > ALUOp [1:0] $end
$var reg 4 ? aluControl [3:0] $end
$upscope $end
$scope module branch_unit $end
$var wire 3 @ funct3 [2:0] $end
$var wire 32 A rs2 [31:0] $end
$var wire 32 B rs1 [31:0] $end
$var wire 1 5 branch $end
$var reg 1 - branchTaken $end
$upscope $end
$scope module control $end
$var wire 7 C Opcode [6:0] $end
$var reg 2 D ALUOp [1:0] $end
$var reg 1 6 ALUSrc $end
$var reg 1 5 Branch $end
$var reg 1 4 Jump $end
$var reg 1 3 MemRead $end
$var reg 1 2 MemToReg $end
$var reg 1 1 MemWrite $end
$var reg 1 0 RegWrite $end
$upscope $end
$scope module dmem $end
$var wire 1 3 MemRead $end
$var wire 1 1 MemWrite $end
$var wire 32 E addr [31:0] $end
$var wire 1 ! clk $end
$var wire 32 F writeData [31:0] $end
$var reg 32 G readData [31:0] $end
$upscope $end
$scope module imem $end
$var wire 32 H instrucao [31:0] $end
$var wire 32 I addr [31:0] $end
$var integer 32 J i [31:0] $end
$upscope $end
$scope module immGen $end
$var wire 32 K instrucoes [31:0] $end
$var wire 7 L opcode [6:0] $end
$var reg 32 M imediato [31:0] $end
$upscope $end
$scope module pcouter $end
$var wire 1 - branch $end
$var wire 1 ! clk $end
$var wire 1 N halt $end
$var wire 32 O immediate [31:0] $end
$var wire 1 # jalr $end
$var wire 1 4 jump $end
$var wire 1 " reset $end
$var wire 1 $ zero $end
$var wire 32 P rs1 [31:0] $end
$var reg 32 Q nextPc [31:0] $end
$var reg 32 R pc [31:0] $end
$upscope $end
$scope module regfile $end
$var wire 1 ! clk $end
$var wire 5 S rd [4:0] $end
$var wire 1 0 regWrite $end
$var wire 5 T rs1 [4:0] $end
$var wire 5 U rs2 [4:0] $end
$var wire 32 V writeData [31:0] $end
$var wire 32 W readData2 [31:0] $end
$var wire 32 X readData1 [31:0] $end
$var integer 32 Y i [31:0] $end
$upscope $end
$upscope $end
$upscope $end
$enddefinitions $end
$comment Show the parameter values. $end
$dumpall
$end
#0
$dumpvars
b100000 Y
b0 X
b0 W
b0 V
b0 U
b0 T
b1 S
b0 R
b100 Q
b0 P
b0 O
0N
b0 M
b10011 L
b10010011 K
b100000000 J
b0 I
b10010011 H
b0 G
b0 F
b0 E
b11 D
b10011 C
b0 B
b0 A
b0 @
b0 ?
b11 >
b0 =
b0 <
b0 ;
b0 :
b0 9
b0 8
b11 7
16
05
04
03
02
01
10
b0 /
b0 .
0-
b0 ,
b10010011 +
b0 *
b0 )
b0 (
b0 '
b0 &
b0 %
1$
z#
1"
0!
$end
#5
1!
#10
0!
0"
#15
b1 %
b1 V
0$
b1 .
b1 ;
b1 E
b1 &
b1 8
b1 ,
b1 M
b1 O
b10 S
b1 U
b100000000000100010011 +
b100000000000100010011 H
b100000000000100010011 K
b1000 Q
b100 )
b100 I
b100 R
1!
#20
0!
#25
b1010 %
b1010 V
b1010 .
b1010 ;
b1010 E
b1010 &
b1010 8
b1010 ,
b1010 M
b1010 O
b11 S
b1010 U
b101000000000000110010011 +
b101000000000000110010011 H
b101000000000000110010011 K
b1100 Q
b1000 )
b1000 I
b1000 R
1!
#30
0!
#35
b1 %
b1 V
b1 .
b1 ;
b1 E
b1 &
b1 8
b1 '
b1 A
b1 F
b1 W
b10 7
b10 >
b10 D
06
10
b0 ,
b0 M
b0 O
b110011 L
b100 S
b10 U
b1 T
b110011 C
b1000001000001000110011 +
b1000001000001000110011 H
b1000001000001000110011 K
b10000 Q
b1100 )
b1100 I
b1100 R
1!
#40
0!
#45
b1 %
b1 V
b0 &
b0 8
b1 .
b1 ;
b1 E
b0 '
b0 A
b0 F
b0 W
b1 (
b1 :
b1 B
b1 P
b1 X
b1 S
b0 U
b10 T
b10000000010110011 +
b10000000010110011 H
b10000000010110011 K
b10100 Q
b10000 )
b10000 I
b10000 R
1!
#50
0!
#55
b10 S
b100 T
b100000000100110011 +
b100000000100110011 H
b100000000100110011 K
b11000 Q
b10100 )
b10100 I
b10100 R
1!
#60
0!
#65
b1001 %
b1001 V
b1001 .
b1001 ;
b1001 E
b11111111111111111111111111111111 &
b11111111111111111111111111111111 8
b1010 (
b1010 :
b1010 B
b1010 P
b1010 X
16
b11 7
b11 >
b11 D
10
b11111111111111111111111111111111 ,
b11111111111111111111111111111111 M
b11111111111111111111111111111111 O
b10011 L
b1111111 =
b11 S
b11111 U
b11 T
b10011 C
b11111111111100011000000110010011 +
b11111111111100011000000110010011 H
b11111111111100011000000110010011 K
b11100 Q
b11000 )
b11000 I
b11000 R
1!
#70
0!
#75
b1001 %
b1001 V
b0 &
b0 8
b1 /
b1 9
b1 ?
15
b1 7
b1 >
b1 D
06
00
b1001 .
b1001 ;
b1001 E
b1000 ,
b1000 M
b1000 O
b1100011 L
b0 =
b1000 S
b0 U
b1100011 C
b1001 (
b1001 :
b1001 B
b1001 P
b1001 X
b11000010001100011 +
b11000010001100011 H
b11000010001100011 K
b100000 Q
b11100 )
b11100 I
b11100 R
1!
#80
0!
#85
b0 %
b0 V
1$
b0 .
b0 ;
b0 E
b0 /
b0 9
b0 ?
b0 (
b0 :
b0 B
b0 P
b0 X
14
10
b0 7
b0 >
b0 D
05
b11111111111111111111111111101100 ,
b11111111111111111111111111101100 M
b11111111111111111111111111101100 O
b1101111 L
b111 @
b1111111 =
b111 <
b0 S
b1101 U
b11111 T
b1101111 C
b11111110110111111111000001101111 +
b11111110110111111111000001101111 H
b11111110110111111111000001101111 K
b1100 Q
b100000 )
b100000 I
b100000 R
1!
#90
0!
#95
b10 %
b10 V
b1 &
b1 8
0$
b10 .
b10 ;
b10 E
b1 '
b1 A
b1 F
b1 W
b1 (
b1 :
b1 B
b1 P
b1 X
b10 7
b10 >
b10 D
04
10
b0 ,
b0 M
b0 O
b110011 L
b0 @
b0 =
b0 <
b100 S
b10 U
b1 T
b110011 C
b1000001000001000110011 +
b1000001000001000110011 H
b1000001000001000110011 K
b10000 Q
b1100 )
b1100 I
b1100 R
1!
#100
0!
#105
b1 %
b1 V
b1 .
b1 ;
b1 E
b0 &
b0 8
b0 '
b0 A
b0 F
b0 W
b1 S
b0 U
b10 T
b10000000010110011 +
b10000000010110011 H
b10000000010110011 K
b10100 Q
b10000 )
b10000 I
b10000 R
1!
#110
0!
#115
b10 %
b10 V
b10 .
b10 ;
b10 E
b10 (
b10 :
b10 B
b10 P
b10 X
b10 S
b100 T
b100000000100110011 +
b100000000100110011 H
b100000000100110011 K
b11000 Q
b10100 )
b10100 I
b10100 R
1!
#120
0!
#125
b1000 %
b1000 V
b1000 .
b1000 ;
b1000 E
b11111111111111111111111111111111 &
b11111111111111111111111111111111 8
b1001 (
b1001 :
b1001 B
b1001 P
b1001 X
16
b11 7
b11 >
b11 D
10
b11111111111111111111111111111111 ,
b11111111111111111111111111111111 M
b11111111111111111111111111111111 O
b10011 L
b1111111 =
b11 S
b11111 U
b11 T
b10011 C
b11111111111100011000000110010011 +
b11111111111100011000000110010011 H
b11111111111100011000000110010011 K
b11100 Q
b11000 )
b11000 I
b11000 R
1!
#130
0!
#135
b1000 %
b1000 V
b0 &
b0 8
b1 /
b1 9
b1 ?
15
b1 7
b1 >
b1 D
06
00
b1000 .
b1000 ;
b1000 E
b1000 ,
b1000 M
b1000 O
b1100011 L
b0 =
b1000 S
b0 U
b1100011 C
b1000 (
b1000 :
b1000 B
b1000 P
b1000 X
b11000010001100011 +
b11000010001100011 H
b11000010001100011 K
b100000 Q
b11100 )
b11100 I
b11100 R
1!
#140
0!
#145
b0 %
b0 V
1$
b0 .
b0 ;
b0 E
b0 /
b0 9
b0 ?
b0 (
b0 :
b0 B
b0 P
b0 X
14
10
b0 7
b0 >
b0 D
05
b11111111111111111111111111101100 ,
b11111111111111111111111111101100 M
b11111111111111111111111111101100 O
b1101111 L
b111 @
b1111111 =
b111 <
b0 S
b1101 U
b11111 T
b1101111 C
b11111110110111111111000001101111 +
b11111110110111111111000001101111 H
b11111110110111111111000001101111 K
b1100 Q
b100000 )
b100000 I
b100000 R
1!
#150
0!
#155
b11 %
b11 V
b10 &
b10 8
0$
b11 .
b11 ;
b11 E
b10 '
b10 A
b10 F
b10 W
b1 (
b1 :
b1 B
b1 P
b1 X
b10 7
b10 >
b10 D
04
10
b0 ,
b0 M
b0 O
b110011 L
b0 @
b0 =
b0 <
b100 S
b10 U
b1 T
b110011 C
b1000001000001000110011 +
b1000001000001000110011 H
b1000001000001000110011 K
b10000 Q
b1100 )
b1100 I
b1100 R
1!
#160
0!
#165
b10 %
b10 V
b0 &
b0 8
b10 .
b10 ;
b10 E
b0 '
b0 A
b0 F
b0 W
b10 (
b10 :
b10 B
b10 P
b10 X
b1 S
b0 U
b10 T
b10000000010110011 +
b10000000010110011 H
b10000000010110011 K
b10100 Q
b10000 )
b10000 I
b10000 R
1!
#170
0!
#175
b11 %
b11 V
b11 .
b11 ;
b11 E
b11 (
b11 :
b11 B
b11 P
b11 X
b10 S
b100 T
b100000000100110011 +
b100000000100110011 H
b100000000100110011 K
b11000 Q
b10100 )
b10100 I
b10100 R
1!
#180
0!
#185
b111 %
b111 V
b111 .
b111 ;
b111 E
b11111111111111111111111111111111 &
b11111111111111111111111111111111 8
b1000 (
b1000 :
b1000 B
b1000 P
b1000 X
16
b11 7
b11 >
b11 D
10
b11111111111111111111111111111111 ,
b11111111111111111111111111111111 M
b11111111111111111111111111111111 O
b10011 L
b1111111 =
b11 S
b11111 U
b11 T
b10011 C
b11111111111100011000000110010011 +
b11111111111100011000000110010011 H
b11111111111100011000000110010011 K
b11100 Q
b11000 )
b11000 I
b11000 R
1!
#190
0!
#195
b111 %
b111 V
b0 &
b0 8
b1 /
b1 9
b1 ?
15
b1 7
b1 >
b1 D
06
00
b111 .
b111 ;
b111 E
b1000 ,
b1000 M
b1000 O
b1100011 L
b0 =
b1000 S
b0 U
b1100011 C
b111 (
b111 :
b111 B
b111 P
b111 X
b11000010001100011 +
b11000010001100011 H
b11000010001100011 K
b100000 Q
b11100 )
b11100 I
b11100 R
1!
#200
0!
#205
b0 %
b0 V
1$
b0 .
b0 ;
b0 E
b0 /
b0 9
b0 ?
b0 (
b0 :
b0 B
b0 P
b0 X
14
10
b0 7
b0 >
b0 D
05
b11111111111111111111111111101100 ,
b11111111111111111111111111101100 M
b11111111111111111111111111101100 O
b1101111 L
b111 @
b1111111 =
b111 <
b0 S
b1101 U
b11111 T
b1101111 C
b11111110110111111111000001101111 +
b11111110110111111111000001101111 H
b11111110110111111111000001101111 K
b1100 Q
b100000 )
b100000 I
b100000 R
1!
#210
0!
#215
b101 %
b101 V
b11 &
b11 8
0$
b101 .
b101 ;
b101 E
b11 '
b11 A
b11 F
b11 W
b10 (
b10 :
b10 B
b10 P
b10 X
b10 7
b10 >
b10 D
04
10
b0 ,
b0 M
b0 O
b110011 L
b0 @
b0 =
b0 <
b100 S
b10 U
b1 T
b110011 C
b1000001000001000110011 +
b1000001000001000110011 H
b1000001000001000110011 K
b10000 Q
b1100 )
b1100 I
b1100 R
1!
#220
0!
#225
b11 %
b11 V
b0 &
b0 8
b11 .
b11 ;
b11 E
b0 '
b0 A
b0 F
b0 W
b11 (
b11 :
b11 B
b11 P
b11 X
b1 S
b0 U
b10 T
b10000000010110011 +
b10000000010110011 H
b10000000010110011 K
b10100 Q
b10000 )
b10000 I
b10000 R
1!
#230
0!
#235
b101 %
b101 V
b101 .
b101 ;
b101 E
b101 (
b101 :
b101 B
b101 P
b101 X
b10 S
b100 T
b100000000100110011 +
b100000000100110011 H
b100000000100110011 K
b11000 Q
b10100 )
b10100 I
b10100 R
1!
#240
0!
#245
b110 %
b110 V
b110 .
b110 ;
b110 E
b11111111111111111111111111111111 &
b11111111111111111111111111111111 8
b111 (
b111 :
b111 B
b111 P
b111 X
16
b11 7
b11 >
b11 D
10
b11111111111111111111111111111111 ,
b11111111111111111111111111111111 M
b11111111111111111111111111111111 O
b10011 L
b1111111 =
b11 S
b11111 U
b11 T
b10011 C
b11111111111100011000000110010011 +
b11111111111100011000000110010011 H
b11111111111100011000000110010011 K
b11100 Q
b11000 )
b11000 I
b11000 R
1!
#250
0!
#255
b110 %
b110 V
b0 &
b0 8
b1 /
b1 9
b1 ?
15
b1 7
b1 >
b1 D
06
00
b110 .
b110 ;
b110 E
b1000 ,
b1000 M
b1000 O
b1100011 L
b0 =
b1000 S
b0 U
b1100011 C
b110 (
b110 :
b110 B
b110 P
b110 X
b11000010001100011 +
b11000010001100011 H
b11000010001100011 K
b100000 Q
b11100 )
b11100 I
b11100 R
1!
#260
0!
#265
b0 %
b0 V
1$
b0 .
b0 ;
b0 E
b0 /
b0 9
b0 ?
b0 (
b0 :
b0 B
b0 P
b0 X
14
10
b0 7
b0 >
b0 D
05
b11111111111111111111111111101100 ,
b11111111111111111111111111101100 M
b11111111111111111111111111101100 O
b1101111 L
b111 @
b1111111 =
b111 <
b0 S
b1101 U
b11111 T
b1101111 C
b11111110110111111111000001101111 +
b11111110110111111111000001101111 H
b11111110110111111111000001101111 K
b1100 Q
b100000 )
b100000 I
b100000 R
1!
#270
0!
#275
b1000 %
b1000 V
b101 &
b101 8
0$
b1000 .
b1000 ;
b1000 E
b101 '
b101 A
b101 F
b101 W
b11 (
b11 :
b11 B
b11 P
b11 X
b10 7
b10 >
b10 D
04
10
b0 ,
b0 M
b0 O
b110011 L
b0 @
b0 =
b0 <
b100 S
b10 U
b1 T
b110011 C
b1000001000001000110011 +
b1000001000001000110011 H
b1000001000001000110011 K
b10000 Q
b1100 )
b1100 I
b1100 R
1!
#280
0!
#285
b101 %
b101 V
b0 &
b0 8
b101 .
b101 ;
b101 E
b0 '
b0 A
b0 F
b0 W
b101 (
b101 :
b101 B
b101 P
b101 X
b1 S
b0 U
b10 T
b10000000010110011 +
b10000000010110011 H
b10000000010110011 K
b10100 Q
b10000 )
b10000 I
b10000 R
1!
#290
0!
#295
b1000 %
b1000 V
b1000 .
b1000 ;
b1000 E
b1000 (
b1000 :
b1000 B
b1000 P
b1000 X
b10 S
b100 T
b100000000100110011 +
b100000000100110011 H
b100000000100110011 K
b11000 Q
b10100 )
b10100 I
b10100 R
1!
#300
0!
#305
b101 %
b101 V
b101 .
b101 ;
b101 E
b11111111111111111111111111111111 &
b11111111111111111111111111111111 8
b110 (
b110 :
b110 B
b110 P
b110 X
16
b11 7
b11 >
b11 D
10
b11111111111111111111111111111111 ,
b11111111111111111111111111111111 M
b11111111111111111111111111111111 O
b10011 L
b1111111 =
b11 S
b11111 U
b11 T
b10011 C
b11111111111100011000000110010011 +
b11111111111100011000000110010011 H
b11111111111100011000000110010011 K
b11100 Q
b11000 )
b11000 I
b11000 R
1!
#310
0!
#315
b101 %
b101 V
b0 &
b0 8
b1 /
b1 9
b1 ?
15
b1 7
b1 >
b1 D
06
00
b101 .
b101 ;
b101 E
b1000 ,
b1000 M
b1000 O
b1100011 L
b0 =
b1000 S
b0 U
b1100011 C
b101 (
b101 :
b101 B
b101 P
b101 X
b11000010001100011 +
b11000010001100011 H
b11000010001100011 K
b100000 Q
b11100 )
b11100 I
b11100 R
1!
#320
0!
#325
b0 %
b0 V
1$
b0 .
b0 ;
b0 E
b0 /
b0 9
b0 ?
b0 (
b0 :
b0 B
b0 P
b0 X
14
10
b0 7
b0 >
b0 D
05
b11111111111111111111111111101100 ,
b11111111111111111111111111101100 M
b11111111111111111111111111101100 O
b1101111 L
b111 @
b1111111 =
b111 <
b0 S
b1101 U
b11111 T
b1101111 C
b11111110110111111111000001101111 +
b11111110110111111111000001101111 H
b11111110110111111111000001101111 K
b1100 Q
b100000 )
b100000 I
b100000 R
1!
#330
0!
#335
b1101 %
b1101 V
b1000 &
b1000 8
0$
b1101 .
b1101 ;
b1101 E
b1000 '
b1000 A
b1000 F
b1000 W
b101 (
b101 :
b101 B
b101 P
b101 X
b10 7
b10 >
b10 D
04
10
b0 ,
b0 M
b0 O
b110011 L
b0 @
b0 =
b0 <
b100 S
b10 U
b1 T
b110011 C
b1000001000001000110011 +
b1000001000001000110011 H
b1000001000001000110011 K
b10000 Q
b1100 )
b1100 I
b1100 R
1!
#340
0!
#345
b1000 %
b1000 V
b0 &
b0 8
b1000 .
b1000 ;
b1000 E
b0 '
b0 A
b0 F
b0 W
b1000 (
b1000 :
b1000 B
b1000 P
b1000 X
b1 S
b0 U
b10 T
b10000000010110011 +
b10000000010110011 H
b10000000010110011 K
b10100 Q
b10000 )
b10000 I
b10000 R
1!
#350
0!
#355
b1101 %
b1101 V
b1101 .
b1101 ;
b1101 E
b1101 (
b1101 :
b1101 B
b1101 P
b1101 X
b10 S
b100 T
b100000000100110011 +
b100000000100110011 H
b100000000100110011 K
b11000 Q
b10100 )
b10100 I
b10100 R
1!
#360
0!
#365
b100 %
b100 V
b100 .
b100 ;
b100 E
b11111111111111111111111111111111 &
b11111111111111111111111111111111 8
b101 (
b101 :
b101 B
b101 P
b101 X
16
b11 7
b11 >
b11 D
10
b11111111111111111111111111111111 ,
b11111111111111111111111111111111 M
b11111111111111111111111111111111 O
b10011 L
b1111111 =
b11 S
b11111 U
b11 T
b10011 C
b11111111111100011000000110010011 +
b11111111111100011000000110010011 H
b11111111111100011000000110010011 K
b11100 Q
b11000 )
b11000 I
b11000 R
1!
#370
0!
#375
b100 %
b100 V
b0 &
b0 8
b1 /
b1 9
b1 ?
15
b1 7
b1 >
b1 D
06
00
b100 .
b100 ;
b100 E
b1000 ,
b1000 M
b1000 O
b1100011 L
b0 =
b1000 S
b0 U
b1100011 C
b100 (
b100 :
b100 B
b100 P
b100 X
b11000010001100011 +
b11000010001100011 H
b11000010001100011 K
b100000 Q
b11100 )
b11100 I
b11100 R
1!
#380
0!
